socranop/__init__.py
socranop/cli.py
socranop/common.py
socranop/constants.py
socranop/contributors.py
socranop/dbus.py
socranop/dirs.py
socranop/gui.py
socranop/installtool.py
socranop/notepad.py
socranop/data/bash-completion/socranop-ctl
socranop/data/bash-completion/socranop-gui
socranop/data/bash-completion/socranop-installtool
socranop/data/bash-completion/socranop-session-service
socranop/data/dbus-1/socranop.service
socranop/data/man/socranop-ctl.1
socranop/data/man/socranop-gui.1
socranop/data/man/socranop-session-service.1
socranop/data/xdg/io.github.socratools.socranop.128.png
socranop/data/xdg/io.github.socratools.socranop.16.png
socranop/data/xdg/io.github.socratools.socranop.192.png
socranop/data/xdg/io.github.socratools.socranop.24.png
socranop/data/xdg/io.github.socratools.socranop.256.png
socranop/data/xdg/io.github.socratools.socranop.32.png
socranop/data/xdg/io.github.socratools.socranop.48.png
socranop/data/xdg/io.github.socratools.socranop.64.png
socranop/data/xdg/io.github.socratools.socranop.96.png
socranop/data/xdg/io.github.socratools.socranop.desktop
socranop/data/xdg/io.github.socratools.socranop.svg
socranop-0.4.92.dist-info/LICENSE
socranop-0.4.92.dist-info/METADATA
socranop-0.4.92.dist-info/WHEEL
socranop-0.4.92.dist-info/entry_points.txt
socranop-0.4.92.dist-info/top_level.txt
socranop-0.4.92.dist-info/RECORD
