Metadata-Version: 2.1
Name: socranop
Version: 0.4.92
Summary: Soundcraft Notepad control utilities
Home-page: https://github.com/socratools/socranop
Author: Jim Ramsay
Author-email: i.am@jimramsay.com
License: MIT
Platform: UNKNOWN
Classifier: Programming Language :: Python :: 3
Classifier: Programming Language :: Python :: 3.6
Classifier: Programming Language :: Python :: 3.7
Classifier: Programming Language :: Python :: 3.8
Classifier: Programming Language :: Python :: 3.9
Classifier: Programming Language :: Python :: 3.10
Classifier: License :: OSI Approved :: MIT License
Classifier: Operating System :: OS Independent
Classifier: Topic :: Multimedia :: Sound/Audio :: Mixers
Requires-Python: >=3.6
Requires-Dist: pyusb
Requires-Dist: pydbus
